pyeventsummary/__init__.py
pyeventsummary/pyeventsummary.py
pyeventsummary/static.py
pyeventsummary-0.0.18.dist-info/LICENSE
pyeventsummary-0.0.18.dist-info/METADATA
pyeventsummary-0.0.18.dist-info/WHEEL
pyeventsummary-0.0.18.dist-info/top_level.txt
pyeventsummary-0.0.18.dist-info/RECORD
