Metadata-Version: 2.1
Name: pyeventsummary
Version: 0.0.18
Summary: pyeventsummary is a way to aggregate and report on a host of errors and actions
Home-page: https://veltzer.github.io/pyeventsummary
Download-URL: https://github.com/veltzer/pyeventsummary
Author: Mark Veltzer
Author-email: mark.veltzer@gmail.com
Maintainer: Mark Veltzer
Maintainer-email: mark.veltzer@gmail.com
License: MIT
Keywords: python,summary,errors,actions,aggregate,print,enum
Platform: python3
Classifier: Development Status :: 4 - Beta
Classifier: Environment :: Console
Classifier: Operating System :: OS Independent
Classifier: Programming Language :: Python
Classifier: Programming Language :: Python :: 3
Classifier: Programming Language :: Python :: 3 :: Only
Classifier: Programming Language :: Python :: 3.11
Classifier: Topic :: Utilities
Classifier: License :: OSI Approved :: MIT License
License-File: LICENSE
